ipyauth/__init__.py
ipyauth/__meta__.py
ipyauth/ipyauth_callback/__init__.py
ipyauth/ipyauth_callback/ipyauth.json
ipyauth/ipyauth_callback/server_extension.py
ipyauth/ipyauth_callback/templates/index.html
ipyauth/ipyauth_callback/templates/assets/main.js
ipyauth/ipyauth_callback/templates/assets/util.js
ipyauth/ipyauth_widget/__init__.py
ipyauth/ipyauth_widget/_config.py
ipyauth/ipyauth_widget/_params_auth0.py
ipyauth/ipyauth_widget/_params_google.py
ipyauth/ipyauth_widget/_params_keycloak.py
ipyauth/ipyauth_widget/_params_sgconnect.py
ipyauth/ipyauth_widget/_util.py
ipyauth/ipyauth_widget/_widget_box.py
ipyauth/ipyauth_widget/ipyauth.json
ipyauth/ipyauth_widget/img/auth0-logo.png
ipyauth/ipyauth_widget/img/google-logo.png
ipyauth/ipyauth_widget/img/keycloak-logo.png
ipyauth/ipyauth_widget/img/sg-logo.png
ipyauth/ipyauth_widget/static/extension.js
ipyauth/ipyauth_widget/static/index.js
ipyauth/ipyauth_widget/static/index.js.map
ipyauth_keycloak-0.3.0.data/data/etc/jupyter/jupyter_notebook_config.d/ipyauth.json
ipyauth_keycloak-0.3.0.data/data/etc/jupyter/nbconfig/notebook.d/ipyauth.json
ipyauth_keycloak-0.3.0.data/data/share/jupyter/nbextensions/ipyauth/extension.js
ipyauth_keycloak-0.3.0.data/data/share/jupyter/nbextensions/ipyauth/index.js
ipyauth_keycloak-0.3.0.data/data/share/jupyter/nbextensions/ipyauth/index.js.map
ipyauth_keycloak-0.3.0.dist-info/LICENSE
ipyauth_keycloak-0.3.0.dist-info/METADATA
ipyauth_keycloak-0.3.0.dist-info/WHEEL
ipyauth_keycloak-0.3.0.dist-info/top_level.txt
ipyauth_keycloak-0.3.0.dist-info/RECORD
